ask_sdk_local_debug/__init__.py
ask_sdk_local_debug/__version__.py
ask_sdk_local_debug/exception.py
ask_sdk_local_debug/local_debugger.py
ask_sdk_local_debug/local_debugger_invoker.py
ask_sdk_local_debug/py.typed
ask_sdk_local_debug/client/__init__.py
ask_sdk_local_debug/client/abstract_websocket_client.py
ask_sdk_local_debug/client/autobahn_client.py
ask_sdk_local_debug/client/autobahn_client_protocol.py
ask_sdk_local_debug/client/py.typed
ask_sdk_local_debug/config/__init__.py
ask_sdk_local_debug/config/client_config.py
ask_sdk_local_debug/config/constant_config.py
ask_sdk_local_debug/config/py.typed
ask_sdk_local_debug/config/region.py
ask_sdk_local_debug/config/skill_invoker_config.py
ask_sdk_local_debug/config/websocket_config.py
ask_sdk_local_debug/util/__init__.py
ask_sdk_local_debug/util/parser.py
ask_sdk_local_debug/util/py.typed
ask_sdk_local_debug/util/response_util.py
ask_sdk_local_debug/util/serializer.py
ask_sdk_local_debug/util/websocket_util.py
ask_sdk_local_debug-1.1.0.dist-info/METADATA
ask_sdk_local_debug-1.1.0.dist-info/RECORD
ask_sdk_local_debug-1.1.0.dist-info/WHEEL
ask_sdk_local_debug-1.1.0.dist-info/top_level.txt
