Metadata-Version: 2.1
Name: ask-sdk-local-debug
Version: 1.1.0
Summary: The ASK SDK Local Debug package provides Alexa Skills Kit debugger functionality
Home-page: https://github.com/alexa/alexa-skills-kit-sdk-for-python
Author: Alexa Skills Kit
Author-email: ask-sdk-dynamic@amazon.com
License: Apache 2.0
Keywords: ASK SDK,Alexa Skills Kit,Alexa,Debug
Platform: UNKNOWN
Classifier: Development Status :: 5 - Production/Stable
Classifier: Intended Audience :: Developers
Classifier: Natural Language :: English
Classifier: License :: OSI Approved :: Apache Software License
Classifier: Programming Language :: Python
Classifier: Programming Language :: Python :: 3
Classifier: Programming Language :: Python :: 3.6
Classifier: Programming Language :: Python :: 3.7
Requires-Python: !=3.0.*, !=3.1.*, !=3.2.*, !=3.3.*, !=3.4.*, !=3.5.*
Requires-Dist: ask-sdk-model (>=1.23.1)
Requires-Dist: ask-sdk-model-runtime
Requires-Dist: autobahn[twisted,encryption] (>=20.4.3)
Requires-Dist: requests
